efm8/__init__.py
efm8/__main__.py
efm8/py.typed
efm8/u2fzero.py
efm8-0.0.4.dist-info/LICENSE
efm8-0.0.4.dist-info/METADATA
efm8-0.0.4.dist-info/WHEEL
efm8-0.0.4.dist-info/entry_points.txt
efm8-0.0.4.dist-info/top_level.txt
efm8-0.0.4.dist-info/RECORD
