Metadata-Version: 2.1
Name: efm8
Version: 0.0.4
Summary: Flash via AN945: EFM8 Factory Bootloader HID
Home-page: UNKNOWN
Author: Barnaby Shearer
Author-email: b@zi.is
License: BSD
Keywords: EFM8 AN945 HID Bootloader
Platform: UNKNOWN
Classifier: Development Status :: 5 - Production/Stable
Classifier: Environment :: Console
Classifier: License :: OSI Approved :: BSD License
Classifier: Programming Language :: Python :: 2
Classifier: Programming Language :: Python :: 3
Requires-Python: >=2.7
License-File: LICENSE
Requires-Dist: hidapi (>=0.7.99.post21)
Requires-Dist: pythoncrc (>=1.21)
Requires-Dist: typing ; python_version < "3"
